scp.py
scp-0.14.5.dist-info/LICENSE.txt
scp-0.14.5.dist-info/METADATA
scp-0.14.5.dist-info/WHEEL
scp-0.14.5.dist-info/top_level.txt
scp-0.14.5.dist-info/RECORD
