Metadata-Version: 2.1
Name: scp
Version: 0.14.5
Summary: scp module for paramiko
Home-page: https://github.com/jbardin/scp.py
Author: James Bardin
Author-email: j.bardin@gmail.com
Maintainer: Remi Rampin
Maintainer-email: remi@rampin.org
License: LGPL-2.1-or-later
Keywords: paramiko,ssh,scp,transfer
Platform: UNKNOWN
Classifier: Development Status :: 5 - Production/Stable
Classifier: Intended Audience :: Developers
Classifier: License :: OSI Approved :: GNU Library or Lesser General Public License (LGPL)
Classifier: Operating System :: OS Independent
Classifier: Programming Language :: Python
Classifier: Programming Language :: Python :: 2.6
Classifier: Programming Language :: Python :: 2.7
Classifier: Programming Language :: Python :: 3
Classifier: Topic :: Internet
License-File: LICENSE.txt
